{"config":{"output_file":null,"full_docs":false,"pub_only":true,"reachable_only":true,"distro_crate":false,"signatures":false,"borrow_data":false},"version":"0.19.0","compilation":{"directory":"C:\\Users\\CYM\\scoop\\persist\\rustup\\.cargo\\registry\\src\\github.com-1ecc6299db9ec823\\hyper-tls-0.4.3","program":"C:\\Users\\CYM\\scoop\\persist\\rustup\\.rustup\\toolchains\\stable-x86_64-pc-windows-msvc\\bin\\rls.exe","arguments":["--crate-name","hyper_tls","--edition=2018","C:\\Users\\CYM\\scoop\\persist\\rustup\\.cargo\\registry\\src\\github.com-1ecc6299db9ec823\\hyper-tls-0.4.3\\src\\lib.rs","--json=diagnostic-rendered-ansi","--crate-type","lib","--emit=dep-info,metadata","-C","embed-bitcode=no","-C","debuginfo=2","-C","metadata=9b557b98a7a5ead6","-C","extra-filename=-9b557b98a7a5ead6","--out-dir","c:\\Users\\CYM\\Desktop\\buceaNet\\rust\\target\\rls\\debug\\deps","-L","dependency=c:\\Users\\CYM\\Desktop\\buceaNet\\rust\\target\\rls\\debug\\deps","--extern","bytes=c:\\Users\\CYM\\Desktop\\buceaNet\\rust\\target\\rls\\debug\\deps\\libbytes-c562b6a91c9c3b1f.rmeta","--extern","hyper=c:\\Users\\CYM\\Desktop\\buceaNet\\rust\\target\\rls\\debug\\deps\\libhyper-441c59806d089906.rmeta","--extern","native_tls=c:\\Users\\CYM\\Desktop\\buceaNet\\rust\\target\\rls\\debug\\deps\\libnative_tls-91435f35422a975e.rmeta","--extern","tokio=c:\\Users\\CYM\\Desktop\\buceaNet\\rust\\target\\rls\\debug\\deps\\libtokio-ea9d31de27326b18.rmeta","--extern","tokio_tls=c:\\Users\\CYM\\Desktop\\buceaNet\\rust\\target\\rls\\debug\\deps\\libtokio_tls-76c67d52b2103a42.rmeta","--cap-lints","allow","--error-format=json","--sysroot","C:\\Users\\CYM\\scoop\\persist\\rustup\\.rustup/toolchains/stable-x86_64-pc-windows-msvc"],"output":"c:\\Users\\CYM\\Desktop\\buceaNet\\rust\\target\\rls\\debug\\deps\\libhyper_tls-9b557b98a7a5ead6.rmeta"},"prelude":{"crate_id":{"name":"hyper_tls","disambiguator":[8423614307958162165,9299487838369655388]},"crate_root":"C:\\Users\\CYM\\scoop\\persist\\rustup\\.cargo\\registry\\src\\github.com-1ecc6299db9ec823\\hyper-tls-0.4.3\\src","external_crates":[{"file_name":"C:\\Users\\CYM\\scoop\\persist\\rustup\\.cargo\\registry\\src\\github.com-1ecc6299db9ec823\\hyper-tls-0.4.3\\src\\lib.rs","num":1,"id":{"name":"std","disambiguator":[1921591330338517602,8002743023817837766]}},{"file_name":"C:\\Users\\CYM\\scoop\\persist\\rustup\\.cargo\\registry\\src\\github.com-1ecc6299db9ec823\\hyper-tls-0.4.3\\src\\lib.rs","num":2,"id":{"name":"core","disambiguator":[3294562336267099064,32966444439847392]}},{"file_name":"C:\\Users\\CYM\\scoop\\persist\\rustup\\.cargo\\registry\\src\\github.com-1ecc6299db9ec823\\hyper-tls-0.4.3\\src\\lib.rs","num":3,"id":{"name":"compiler_builtins","disambiguator":[8997478989526601172,15466949633016966289]}},{"file_name":"C:\\Users\\CYM\\scoop\\persist\\rustup\\.cargo\\registry\\src\\github.com-1ecc6299db9ec823\\hyper-tls-0.4.3\\src\\lib.rs","num":4,"id":{"name":"rustc_std_workspace_core","disambiguator":[2630917957276446109,8658156290826251556]}},{"file_name":"C:\\Users\\CYM\\scoop\\persist\\rustup\\.cargo\\registry\\src\\github.com-1ecc6299db9ec823\\hyper-tls-0.4.3\\src\\lib.rs","num":5,"id":{"name":"alloc","disambiguator":[16592919627580665262,9528133364691589515]}},{"file_name":"C:\\Users\\CYM\\scoop\\persist\\rustup\\.cargo\\registry\\src\\github.com-1ecc6299db9ec823\\hyper-tls-0.4.3\\src\\lib.rs","num":6,"id":{"name":"libc","disambiguator":[12745094628986209607,10518202857406436678]}},{"file_name":"C:\\Users\\CYM\\scoop\\persist\\rustup\\.cargo\\registry\\src\\github.com-1ecc6299db9ec823\\hyper-tls-0.4.3\\src\\lib.rs","num":7,"id":{"name":"unwind","disambiguator":[12421643217715303902,5448498891032173630]}},{"file_name":"C:\\Users\\CYM\\scoop\\persist\\rustup\\.cargo\\registry\\src\\github.com-1ecc6299db9ec823\\hyper-tls-0.4.3\\src\\lib.rs","num":8,"id":{"name":"cfg_if","disambiguator":[10471275659107711445,16777480585464664117]}},{"file_name":"C:\\Users\\CYM\\scoop\\persist\\rustup\\.cargo\\registry\\src\\github.com-1ecc6299db9ec823\\hyper-tls-0.4.3\\src\\lib.rs","num":9,"id":{"name":"hashbrown","disambiguator":[5556840401016198219,10246883469141694681]}},{"file_name":"C:\\Users\\CYM\\scoop\\persist\\rustup\\.cargo\\registry\\src\\github.com-1ecc6299db9ec823\\hyper-tls-0.4.3\\src\\lib.rs","num":10,"id":{"name":"rustc_std_workspace_alloc","disambiguator":[5351773000290944944,5461204872568622329]}},{"file_name":"C:\\Users\\CYM\\scoop\\persist\\rustup\\.cargo\\registry\\src\\github.com-1ecc6299db9ec823\\hyper-tls-0.4.3\\src\\lib.rs","num":11,"id":{"name":"rustc_demangle","disambiguator":[1406896991597352872,16715998803959789672]}},{"file_name":"C:\\Users\\CYM\\scoop\\persist\\rustup\\.cargo\\registry\\src\\github.com-1ecc6299db9ec823\\hyper-tls-0.4.3\\src\\lib.rs","num":12,"id":{"name":"panic_unwind","disambiguator":[16017799561494711091,10322761666972095232]}},{"file_name":"C:\\Users\\CYM\\scoop\\persist\\rustup\\.cargo\\registry\\src\\github.com-1ecc6299db9ec823\\hyper-tls-0.4.3\\src\\lib.rs","num":13,"id":{"name":"native_tls","disambiguator":[13363298198413197642,6295441479700063327]}},{"file_name":"C:\\Users\\CYM\\scoop\\persist\\rustup\\.cargo\\registry\\src\\github.com-1ecc6299db9ec823\\hyper-tls-0.4.3\\src\\lib.rs","num":14,"id":{"name":"schannel","disambiguator":[4141151856702533911,448384601469956304]}},{"file_name":"C:\\Users\\CYM\\scoop\\persist\\rustup\\.cargo\\registry\\src\\github.com-1ecc6299db9ec823\\hyper-tls-0.4.3\\src\\lib.rs","num":15,"id":{"name":"winapi","disambiguator":[9808287324151002286,5855267894827219549]}},{"file_name":"C:\\Users\\CYM\\scoop\\persist\\rustup\\.cargo\\registry\\src\\github.com-1ecc6299db9ec823\\hyper-tls-0.4.3\\src\\lib.rs","num":16,"id":{"name":"lazy_static","disambiguator":[11015315125905031475,12457729104174530383]}},{"file_name":"C:\\Users\\CYM\\scoop\\persist\\rustup\\.cargo\\registry\\src\\github.com-1ecc6299db9ec823\\hyper-tls-0.4.3\\src\\client.rs","num":17,"id":{"name":"hyper","disambiguator":[6256511279213147452,12006560573974733039]}},{"file_name":"C:\\Users\\CYM\\scoop\\persist\\rustup\\.cargo\\registry\\src\\github.com-1ecc6299db9ec823\\hyper-tls-0.4.3\\src\\client.rs","num":18,"id":{"name":"tracing","disambiguator":[16619568999801413745,18225702928842745715]}},{"file_name":"C:\\Users\\CYM\\scoop\\persist\\rustup\\.cargo\\registry\\src\\github.com-1ecc6299db9ec823\\hyper-tls-0.4.3\\src\\client.rs","num":19,"id":{"name":"cfg_if","disambiguator":[568027780971654548,7179391208125931855]}},{"file_name":"C:\\Users\\CYM\\scoop\\persist\\rustup\\.cargo\\registry\\src\\github.com-1ecc6299db9ec823\\hyper-tls-0.4.3\\src\\client.rs","num":20,"id":{"name":"log","disambiguator":[15379110767755223413,5996927049130175394]}},{"file_name":"C:\\Users\\CYM\\scoop\\persist\\rustup\\.cargo\\registry\\src\\github.com-1ecc6299db9ec823\\hyper-tls-0.4.3\\src\\client.rs","num":21,"id":{"name":"cfg_if","disambiguator":[3867657372731410738,4213284747709546304]}},{"file_name":"C:\\Users\\CYM\\scoop\\persist\\rustup\\.cargo\\registry\\src\\github.com-1ecc6299db9ec823\\hyper-tls-0.4.3\\src\\client.rs","num":22,"id":{"name":"tracing_core","disambiguator":[10268827835561685147,4208038592277288475]}},{"file_name":"C:\\Users\\CYM\\scoop\\persist\\rustup\\.cargo\\registry\\src\\github.com-1ecc6299db9ec823\\hyper-tls-0.4.3\\src\\client.rs","num":23,"id":{"name":"pin_project_lite","disambiguator":[5630498404159450583,15747214064771415261]}},{"file_name":"C:\\Users\\CYM\\scoop\\persist\\rustup\\.cargo\\registry\\src\\github.com-1ecc6299db9ec823\\hyper-tls-0.4.3\\src\\client.rs","num":24,"id":{"name":"http","disambiguator":[10092164978979447619,8663016981425077758]}},{"file_name":"C:\\Users\\CYM\\scoop\\persist\\rustup\\.cargo\\registry\\src\\github.com-1ecc6299db9ec823\\hyper-tls-0.4.3\\src\\client.rs","num":25,"id":{"name":"fnv","disambiguator":[9339455543216966154,1331402390711887921]}},{"file_name":"C:\\Users\\CYM\\scoop\\persist\\rustup\\.cargo\\registry\\src\\github.com-1ecc6299db9ec823\\hyper-tls-0.4.3\\src\\stream.rs","num":26,"id":{"name":"bytes","disambiguator":[9552923760870349937,2902864437352291715]}},{"file_name":"C:\\Users\\CYM\\scoop\\persist\\rustup\\.cargo\\registry\\src\\github.com-1ecc6299db9ec823\\hyper-tls-0.4.3\\src\\client.rs","num":27,"id":{"name":"itoa","disambiguator":[4651046026635878123,1183047597350836850]}},{"file_name":"C:\\Users\\CYM\\scoop\\persist\\rustup\\.cargo\\registry\\src\\github.com-1ecc6299db9ec823\\hyper-tls-0.4.3\\src\\client.rs","num":28,"id":{"name":"pin_project","disambiguator":[12742648026883208984,8093847737041157529]}},{"file_name":"C:\\Users\\CYM\\scoop\\persist\\rustup\\.cargo\\registry\\src\\github.com-1ecc6299db9ec823\\hyper-tls-0.4.3\\src\\client.rs","num":29,"id":{"name":"pin_project_internal","disambiguator":[17527568345691088981,8320351579889662702]}},{"file_name":"C:\\Users\\CYM\\scoop\\persist\\rustup\\.cargo\\registry\\src\\github.com-1ecc6299db9ec823\\hyper-tls-0.4.3\\src\\client.rs","num":30,"id":{"name":"tokio","disambiguator":[16332255315271353582,2806103517327385928]}},{"file_name":"C:\\Users\\CYM\\scoop\\persist\\rustup\\.cargo\\registry\\src\\github.com-1ecc6299db9ec823\\hyper-tls-0.4.3\\src\\client.rs","num":31,"id":{"name":"pin_project_lite","disambiguator":[11013590228031965115,12313274748512788755]}},{"file_name":"C:\\Users\\CYM\\scoop\\persist\\rustup\\.cargo\\registry\\src\\github.com-1ecc6299db9ec823\\hyper-tls-0.4.3\\src\\client.rs","num":32,"id":{"name":"futures_core","disambiguator":[18323906423729551861,18288256076744076581]}},{"file_name":"C:\\Users\\CYM\\scoop\\persist\\rustup\\.cargo\\registry\\src\\github.com-1ecc6299db9ec823\\hyper-tls-0.4.3\\src\\client.rs","num":33,"id":{"name":"mio","disambiguator":[8470088307214489202,4893165623719371561]}},{"file_name":"C:\\Users\\CYM\\scoop\\persist\\rustup\\.cargo\\registry\\src\\github.com-1ecc6299db9ec823\\hyper-tls-0.4.3\\src\\client.rs","num":34,"id":{"name":"net2","disambiguator":[11677637766462692133,12998158449032731656]}},{"file_name":"C:\\Users\\CYM\\scoop\\persist\\rustup\\.cargo\\registry\\src\\github.com-1ecc6299db9ec823\\hyper-tls-0.4.3\\src\\client.rs","num":35,"id":{"name":"iovec","disambiguator":[14362811575861595234,17849609732206218893]}},{"file_name":"C:\\Users\\CYM\\scoop\\persist\\rustup\\.cargo\\registry\\src\\github.com-1ecc6299db9ec823\\hyper-tls-0.4.3\\src\\client.rs","num":36,"id":{"name":"slab","disambiguator":[16496656217701498672,17248453209429697023]}},{"file_name":"C:\\Users\\CYM\\scoop\\persist\\rustup\\.cargo\\registry\\src\\github.com-1ecc6299db9ec823\\hyper-tls-0.4.3\\src\\client.rs","num":37,"id":{"name":"miow","disambiguator":[2758336478430878177,1435915117991833002]}},{"file_name":"C:\\Users\\CYM\\scoop\\persist\\rustup\\.cargo\\registry\\src\\github.com-1ecc6299db9ec823\\hyper-tls-0.4.3\\src\\client.rs","num":38,"id":{"name":"kernel32","disambiguator":[5019076968606122499,4496016190799858155]}},{"file_name":"C:\\Users\\CYM\\scoop\\persist\\rustup\\.cargo\\registry\\src\\github.com-1ecc6299db9ec823\\hyper-tls-0.4.3\\src\\client.rs","num":39,"id":{"name":"winapi","disambiguator":[4511844273484892874,5607318889416899577]}},{"file_name":"C:\\Users\\CYM\\scoop\\persist\\rustup\\.cargo\\registry\\src\\github.com-1ecc6299db9ec823\\hyper-tls-0.4.3\\src\\client.rs","num":40,"id":{"name":"ws2_32","disambiguator":[11718562796824041481,3773089894223285882]}},{"file_name":"C:\\Users\\CYM\\scoop\\persist\\rustup\\.cargo\\registry\\src\\github.com-1ecc6299db9ec823\\hyper-tls-0.4.3\\src\\client.rs","num":41,"id":{"name":"memchr","disambiguator":[18289417098524568386,6860317565413077001]}},{"file_name":"C:\\Users\\CYM\\scoop\\persist\\rustup\\.cargo\\registry\\src\\github.com-1ecc6299db9ec823\\hyper-tls-0.4.3\\src\\client.rs","num":42,"id":{"name":"futures_util","disambiguator":[753406967843566764,8237425154131375801]}},{"file_name":"C:\\Users\\CYM\\scoop\\persist\\rustup\\.cargo\\registry\\src\\github.com-1ecc6299db9ec823\\hyper-tls-0.4.3\\src\\client.rs","num":43,"id":{"name":"pin_utils","disambiguator":[15792880664098840853,11768124074165089136]}},{"file_name":"C:\\Users\\CYM\\scoop\\persist\\rustup\\.cargo\\registry\\src\\github.com-1ecc6299db9ec823\\hyper-tls-0.4.3\\src\\client.rs","num":44,"id":{"name":"futures_task","disambiguator":[13907587114840252980,17060793695003329038]}},{"file_name":"C:\\Users\\CYM\\scoop\\persist\\rustup\\.cargo\\registry\\src\\github.com-1ecc6299db9ec823\\hyper-tls-0.4.3\\src\\client.rs","num":45,"id":{"name":"http_body","disambiguator":[14304793023838021559,14378315792443387654]}},{"file_name":"C:\\Users\\CYM\\scoop\\persist\\rustup\\.cargo\\registry\\src\\github.com-1ecc6299db9ec823\\hyper-tls-0.4.3\\src\\client.rs","num":46,"id":{"name":"futures_channel","disambiguator":[5057474994421673041,3834950784254925323]}},{"file_name":"C:\\Users\\CYM\\scoop\\persist\\rustup\\.cargo\\registry\\src\\github.com-1ecc6299db9ec823\\hyper-tls-0.4.3\\src\\client.rs","num":47,"id":{"name":"tower_service","disambiguator":[11756342553139389319,16735292665373542883]}},{"file_name":"C:\\Users\\CYM\\scoop\\persist\\rustup\\.cargo\\registry\\src\\github.com-1ecc6299db9ec823\\hyper-tls-0.4.3\\src\\client.rs","num":48,"id":{"name":"socket2","disambiguator":[100899457709120453,8524946199460912799]}},{"file_name":"C:\\Users\\CYM\\scoop\\persist\\rustup\\.cargo\\registry\\src\\github.com-1ecc6299db9ec823\\hyper-tls-0.4.3\\src\\client.rs","num":49,"id":{"name":"httpdate","disambiguator":[13849007661198972718,4719823431011763774]}},{"file_name":"C:\\Users\\CYM\\scoop\\persist\\rustup\\.cargo\\registry\\src\\github.com-1ecc6299db9ec823\\hyper-tls-0.4.3\\src\\client.rs","num":50,"id":{"name":"h2","disambiguator":[7885959406912806714,7077518718790953641]}},{"file_name":"C:\\Users\\CYM\\scoop\\persist\\rustup\\.cargo\\registry\\src\\github.com-1ecc6299db9ec823\\hyper-tls-0.4.3\\src\\client.rs","num":51,"id":{"name":"tokio_util","disambiguator":[2502550961659134868,15169158652309777891]}},{"file_name":"C:\\Users\\CYM\\scoop\\persist\\rustup\\.cargo\\registry\\src\\github.com-1ecc6299db9ec823\\hyper-tls-0.4.3\\src\\client.rs","num":52,"id":{"name":"futures_sink","disambiguator":[4938085669323504576,5109072820275941245]}},{"file_name":"C:\\Users\\CYM\\scoop\\persist\\rustup\\.cargo\\registry\\src\\github.com-1ecc6299db9ec823\\hyper-tls-0.4.3\\src\\client.rs","num":53,"id":{"name":"indexmap","disambiguator":[9121931200128795239,13337305548027973605]}},{"file_name":"C:\\Users\\CYM\\scoop\\persist\\rustup\\.cargo\\registry\\src\\github.com-1ecc6299db9ec823\\hyper-tls-0.4.3\\src\\client.rs","num":54,"id":{"name":"hashbrown","disambiguator":[16958428409950773024,10042814692494451166]}},{"file_name":"C:\\Users\\CYM\\scoop\\persist\\rustup\\.cargo\\registry\\src\\github.com-1ecc6299db9ec823\\hyper-tls-0.4.3\\src\\client.rs","num":55,"id":{"name":"tracing_futures","disambiguator":[16949505858602531578,3447557153725342919]}},{"file_name":"C:\\Users\\CYM\\scoop\\persist\\rustup\\.cargo\\registry\\src\\github.com-1ecc6299db9ec823\\hyper-tls-0.4.3\\src\\client.rs","num":56,"id":{"name":"pin_project","disambiguator":[10930773153632645184,8369865701026988739]}},{"file_name":"C:\\Users\\CYM\\scoop\\persist\\rustup\\.cargo\\registry\\src\\github.com-1ecc6299db9ec823\\hyper-tls-0.4.3\\src\\client.rs","num":57,"id":{"name":"pin_project_internal","disambiguator":[2435026410404827857,1301548706598931061]}},{"file_name":"C:\\Users\\CYM\\scoop\\persist\\rustup\\.cargo\\registry\\src\\github.com-1ecc6299db9ec823\\hyper-tls-0.4.3\\src\\client.rs","num":58,"id":{"name":"want","disambiguator":[10629932827773275762,615566502107692655]}},{"file_name":"C:\\Users\\CYM\\scoop\\persist\\rustup\\.cargo\\registry\\src\\github.com-1ecc6299db9ec823\\hyper-tls-0.4.3\\src\\client.rs","num":59,"id":{"name":"try_lock","disambiguator":[9135003385897780376,4140412404889327538]}},{"file_name":"C:\\Users\\CYM\\scoop\\persist\\rustup\\.cargo\\registry\\src\\github.com-1ecc6299db9ec823\\hyper-tls-0.4.3\\src\\client.rs","num":60,"id":{"name":"httparse","disambiguator":[1924480497139483258,15885749495542701948]}},{"file_name":"C:\\Users\\CYM\\scoop\\persist\\rustup\\.cargo\\registry\\src\\github.com-1ecc6299db9ec823\\hyper-tls-0.4.3\\src\\client.rs","num":61,"id":{"name":"tokio_tls","disambiguator":[6118329785763309219,11545458275652283314]}}],"span":{"file_name":"C:\\Users\\CYM\\scoop\\persist\\rustup\\.cargo\\registry\\src\\github.com-1ecc6299db9ec823\\hyper-tls-0.4.3\\src\\lib.rs","byte_start":0,"byte_end":862,"line_start":1,"line_end":35,"column_start":1,"column_end":12}},"imports":[{"kind":"Use","ref_id":{"krate":0,"index":61},"span":{"file_name":"C:\\Users\\CYM\\scoop\\persist\\rustup\\.cargo\\registry\\src\\github.com-1ecc6299db9ec823\\hyper-tls-0.4.3\\src\\lib.rs","byte_start":757,"byte_end":772,"line_start":31,"line_end":31,"column_start":18,"column_end":33},"alias_span":null,"name":"HttpsConnecting","value":"","parent":{"krate":0,"index":0}},{"kind":"Use","ref_id":{"krate":0,"index":125},"span":{"file_name":"C:\\Users\\CYM\\scoop\\persist\\rustup\\.cargo\\registry\\src\\github.com-1ecc6299db9ec823\\hyper-tls-0.4.3\\src\\lib.rs","byte_start":774,"byte_end":788,"line_start":31,"line_end":31,"column_start":35,"column_end":49},"alias_span":null,"name":"HttpsConnector","value":"","parent":{"krate":0,"index":0}},{"kind":"Use","ref_id":{"krate":0,"index":92},"span":{"file_name":"C:\\Users\\CYM\\scoop\\persist\\rustup\\.cargo\\registry\\src\\github.com-1ecc6299db9ec823\\hyper-tls-0.4.3\\src\\lib.rs","byte_start":808,"byte_end":824,"line_start":32,"line_end":32,"column_start":18,"column_end":34},"alias_span":null,"name":"MaybeHttpsStream","value":"","parent":{"krate":0,"index":0}},{"kind":"Use","ref_id":{"krate":61,"index":135},"span":{"file_name":"C:\\Users\\CYM\\scoop\\persist\\rustup\\.cargo\\registry\\src\\github.com-1ecc6299db9ec823\\hyper-tls-0.4.3\\src\\lib.rs","byte_start":826,"byte_end":835,"line_start":32,"line_end":32,"column_start":36,"column_end":45},"alias_span":null,"name":"TlsStream","value":"","parent":{"krate":0,"index":0}}],"defs":[{"kind":"Mod","id":{"krate":0,"index":0},"span":{"file_name":"C:\\Users\\CYM\\scoop\\persist\\rustup\\.cargo\\registry\\src\\github.com-1ecc6299db9ec823\\hyper-tls-0.4.3\\src\\lib.rs","byte_start":0,"byte_end":862,"line_start":1,"line_end":35,"column_start":1,"column_end":12},"name":"","qualname":"::","value":"C:\\Users\\CYM\\scoop\\persist\\rustup\\.cargo\\registry\\src\\github.com-1ecc6299db9ec823\\hyper-tls-0.4.3\\src\\lib.rs","parent":null,"children":[{"krate":0,"index":1},{"krate":0,"index":2},{"krate":0,"index":3},{"krate":0,"index":4},{"krate":0,"index":5},{"krate":0,"index":6},{"krate":0,"index":7},{"krate":0,"index":8},{"krate":0,"index":9},{"krate":0,"index":10},{"krate":0,"index":75}],"decl_id":null,"docs":" # hyper-tls","sig":null,"attributes":[{"value":"/ # hyper-tls","span":{"file_name":"C:\\Users\\CYM\\scoop\\persist\\rustup\\.cargo\\registry\\src\\github.com-1ecc6299db9ec823\\hyper-tls-0.4.3\\src\\lib.rs","byte_start":0,"byte_end":15,"line_start":1,"line_end":1,"column_start":1,"column_end":16}},{"value":"/","span":{"file_name":"C:\\Users\\CYM\\scoop\\persist\\rustup\\.cargo\\registry\\src\\github.com-1ecc6299db9ec823\\hyper-tls-0.4.3\\src\\lib.rs","byte_start":16,"byte_end":19,"line_start":2,"line_end":2,"column_start":1,"column_end":4}},{"value":"/ An HTTPS connector to be used with [hyper][].","span":{"file_name":"C:\\Users\\CYM\\scoop\\persist\\rustup\\.cargo\\registry\\src\\github.com-1ecc6299db9ec823\\hyper-tls-0.4.3\\src\\lib.rs","byte_start":20,"byte_end":69,"line_start":3,"line_end":3,"column_start":1,"column_end":50}},{"value":"/","span":{"file_name":"C:\\Users\\CYM\\scoop\\persist\\rustup\\.cargo\\registry\\src\\github.com-1ecc6299db9ec823\\hyper-tls-0.4.3\\src\\lib.rs","byte_start":70,"byte_end":73,"line_start":4,"line_end":4,"column_start":1,"column_end":4}},{"value":"/ [hyper]: https://hyper.rs","span":{"file_name":"C:\\Users\\CYM\\scoop\\persist\\rustup\\.cargo\\registry\\src\\github.com-1ecc6299db9ec823\\hyper-tls-0.4.3\\src\\lib.rs","byte_start":74,"byte_end":103,"line_start":5,"line_end":5,"column_start":1,"column_end":30}},{"value":"/","span":{"file_name":"C:\\Users\\CYM\\scoop\\persist\\rustup\\.cargo\\registry\\src\\github.com-1ecc6299db9ec823\\hyper-tls-0.4.3\\src\\lib.rs","byte_start":104,"byte_end":107,"line_start":6,"line_end":6,"column_start":1,"column_end":4}},{"value":"/ ## Example","span":{"file_name":"C:\\Users\\CYM\\scoop\\persist\\rustup\\.cargo\\registry\\src\\github.com-1ecc6299db9ec823\\hyper-tls-0.4.3\\src\\lib.rs","byte_start":108,"byte_end":122,"line_start":7,"line_end":7,"column_start":1,"column_end":15}},{"value":"/","span":{"file_name":"C:\\Users\\CYM\\scoop\\persist\\rustup\\.cargo\\registry\\src\\github.com-1ecc6299db9ec823\\hyper-tls-0.4.3\\src\\lib.rs","byte_start":123,"byte_end":126,"line_start":8,"line_end":8,"column_start":1,"column_end":4}},{"value":"/ ```no_run","span":{"file_name":"C:\\Users\\CYM\\scoop\\persist\\rustup\\.cargo\\registry\\src\\github.com-1ecc6299db9ec823\\hyper-tls-0.4.3\\src\\lib.rs","byte_start":127,"byte_end":140,"line_start":9,"line_end":9,"column_start":1,"column_end":14}},{"value":"/ use hyper_tls::HttpsConnector;","span":{"file_name":"C:\\Users\\CYM\\scoop\\persist\\rustup\\.cargo\\registry\\src\\github.com-1ecc6299db9ec823\\hyper-tls-0.4.3\\src\\lib.rs","byte_start":141,"byte_end":175,"line_start":10,"line_end":10,"column_start":1,"column_end":35}},{"value":"/ use hyper::Client;","span":{"file_name":"C:\\Users\\CYM\\scoop\\persist\\rustup\\.cargo\\registry\\src\\github.com-1ecc6299db9ec823\\hyper-tls-0.4.3\\src\\lib.rs","byte_start":176,"byte_end":198,"line_start":11,"line_end":11,"column_start":1,"column_end":23}},{"value":"/","span":{"file_name":"C:\\Users\\CYM\\scoop\\persist\\rustup\\.cargo\\registry\\src\\github.com-1ecc6299db9ec823\\hyper-tls-0.4.3\\src\\lib.rs","byte_start":199,"byte_end":202,"line_start":12,"line_end":12,"column_start":1,"column_end":4}},{"value":"/ #[tokio::main]","span":{"file_name":"C:\\Users\\CYM\\scoop\\persist\\rustup\\.cargo\\registry\\src\\github.com-1ecc6299db9ec823\\hyper-tls-0.4.3\\src\\lib.rs","byte_start":203,"byte_end":221,"line_start":13,"line_end":13,"column_start":1,"column_end":19}},{"value":"/ async fn main() -> Result<(), Box<dyn std::error::Error>>{","span":{"file_name":"C:\\Users\\CYM\\scoop\\persist\\rustup\\.cargo\\registry\\src\\github.com-1ecc6299db9ec823\\hyper-tls-0.4.3\\src\\lib.rs","byte_start":222,"byte_end":284,"line_start":14,"line_end":14,"column_start":1,"column_end":63}},{"value":"/     let https = HttpsConnector::new();","span":{"file_name":"C:\\Users\\CYM\\scoop\\persist\\rustup\\.cargo\\registry\\src\\github.com-1ecc6299db9ec823\\hyper-tls-0.4.3\\src\\lib.rs","byte_start":285,"byte_end":327,"line_start":15,"line_end":15,"column_start":1,"column_end":43}},{"value":"/     let client = Client::builder().build::<_, hyper::Body>(https);","span":{"file_name":"C:\\Users\\CYM\\scoop\\persist\\rustup\\.cargo\\registry\\src\\github.com-1ecc6299db9ec823\\hyper-tls-0.4.3\\src\\lib.rs","byte_start":328,"byte_end":398,"line_start":16,"line_end":16,"column_start":1,"column_end":71}},{"value":"/","span":{"file_name":"C:\\Users\\CYM\\scoop\\persist\\rustup\\.cargo\\registry\\src\\github.com-1ecc6299db9ec823\\hyper-tls-0.4.3\\src\\lib.rs","byte_start":399,"byte_end":402,"line_start":17,"line_end":17,"column_start":1,"column_end":4}},{"value":"/     let res = client.get(\"https://hyper.rs\".parse()?).await?;","span":{"file_name":"C:\\Users\\CYM\\scoop\\persist\\rustup\\.cargo\\registry\\src\\github.com-1ecc6299db9ec823\\hyper-tls-0.4.3\\src\\lib.rs","byte_start":403,"byte_end":468,"line_start":18,"line_end":18,"column_start":1,"column_end":66}},{"value":"/     assert_eq!(res.status(), 200);","span":{"file_name":"C:\\Users\\CYM\\scoop\\persist\\rustup\\.cargo\\registry\\src\\github.com-1ecc6299db9ec823\\hyper-tls-0.4.3\\src\\lib.rs","byte_start":469,"byte_end":507,"line_start":19,"line_end":19,"column_start":1,"column_end":39}},{"value":"/     Ok(())","span":{"file_name":"C:\\Users\\CYM\\scoop\\persist\\rustup\\.cargo\\registry\\src\\github.com-1ecc6299db9ec823\\hyper-tls-0.4.3\\src\\lib.rs","byte_start":508,"byte_end":522,"line_start":20,"line_end":20,"column_start":1,"column_end":15}},{"value":"/ }","span":{"file_name":"C:\\Users\\CYM\\scoop\\persist\\rustup\\.cargo\\registry\\src\\github.com-1ecc6299db9ec823\\hyper-tls-0.4.3\\src\\lib.rs","byte_start":523,"byte_end":528,"line_start":21,"line_end":21,"column_start":1,"column_end":6}},{"value":"/ ```","span":{"file_name":"C:\\Users\\CYM\\scoop\\persist\\rustup\\.cargo\\registry\\src\\github.com-1ecc6299db9ec823\\hyper-tls-0.4.3\\src\\lib.rs","byte_start":529,"byte_end":536,"line_start":22,"line_end":22,"column_start":1,"column_end":8}},{"value":"deny(missing_docs)","span":{"file_name":"C:\\Users\\CYM\\scoop\\persist\\rustup\\.cargo\\registry\\src\\github.com-1ecc6299db9ec823\\hyper-tls-0.4.3\\src\\lib.rs","byte_start":631,"byte_end":653,"line_start":25,"line_end":25,"column_start":1,"column_end":23}},{"value":"deny(missing_debug_implementations)","span":{"file_name":"C:\\Users\\CYM\\scoop\\persist\\rustup\\.cargo\\registry\\src\\github.com-1ecc6299db9ec823\\hyper-tls-0.4.3\\src\\lib.rs","byte_start":654,"byte_end":693,"line_start":26,"line_end":26,"column_start":1,"column_end":40}}]},{"kind":"Struct","id":{"krate":0,"index":125},"span":{"file_name":"C:\\Users\\CYM\\scoop\\persist\\rustup\\.cargo\\registry\\src\\github.com-1ecc6299db9ec823\\hyper-tls-0.4.3\\src\\client.rs","byte_start":1258,"byte_end":1272,"line_start":16,"line_end":16,"column_start":12,"column_end":26},"name":"HttpsConnector","qualname":"::client::HttpsConnector","value":"HttpsConnector {  }","parent":null,"children":[{"krate":0,"index":127},{"krate":0,"index":128},{"krate":0,"index":129}],"decl_id":null,"docs":" A Connector for the `https` scheme.\n","sig":null,"attributes":[{"value":"/ A Connector for the `https` scheme.","span":{"file_name":"C:\\Users\\CYM\\scoop\\persist\\rustup\\.cargo\\registry\\src\\github.com-1ecc6299db9ec823\\hyper-tls-0.4.3\\src\\client.rs","byte_start":1190,"byte_end":1229,"line_start":14,"line_end":14,"column_start":1,"column_end":40}}]},{"kind":"Method","id":{"krate":0,"index":28},"span":{"file_name":"C:\\Users\\CYM\\scoop\\persist\\rustup\\.cargo\\registry\\src\\github.com-1ecc6299db9ec823\\hyper-tls-0.4.3\\src\\client.rs","byte_start":2128,"byte_end":2131,"line_start":42,"line_end":42,"column_start":12,"column_end":15},"name":"new","qualname":"<HttpsConnector<HttpConnector>>::new","value":"pub fn new() -> Self","parent":null,"children":[],"decl_id":null,"docs":" Construct a new HttpsConnector.","sig":null,"attributes":[{"value":"/ Construct a new HttpsConnector.","span":{"file_name":"C:\\Users\\CYM\\scoop\\persist\\rustup\\.cargo\\registry\\src\\github.com-1ecc6299db9ec823\\hyper-tls-0.4.3\\src\\client.rs","byte_start":1381,"byte_end":1416,"line_start":23,"line_end":23,"column_start":5,"column_end":40}},{"value":"/","span":{"file_name":"C:\\Users\\CYM\\scoop\\persist\\rustup\\.cargo\\registry\\src\\github.com-1ecc6299db9ec823\\hyper-tls-0.4.3\\src\\client.rs","byte_start":1421,"byte_end":1424,"line_start":24,"line_end":24,"column_start":5,"column_end":8}},{"value":"/ This uses hyper's default `HttpConnector`, and default `TlsConnector`.","span":{"file_name":"C:\\Users\\CYM\\scoop\\persist\\rustup\\.cargo\\registry\\src\\github.com-1ecc6299db9ec823\\hyper-tls-0.4.3\\src\\client.rs","byte_start":1429,"byte_end":1503,"line_start":25,"line_end":25,"column_start":5,"column_end":79}},{"value":"/ If you wish to use something besides the defaults, use `From::from`.","span":{"file_name":"C:\\Users\\CYM\\scoop\\persist\\rustup\\.cargo\\registry\\src\\github.com-1ecc6299db9ec823\\hyper-tls-0.4.3\\src\\client.rs","byte_start":1508,"byte_end":1580,"line_start":26,"line_end":26,"column_start":5,"column_end":77}},{"value":"/","span":{"file_name":"C:\\Users\\CYM\\scoop\\persist\\rustup\\.cargo\\registry\\src\\github.com-1ecc6299db9ec823\\hyper-tls-0.4.3\\src\\client.rs","byte_start":1585,"byte_end":1588,"line_start":27,"line_end":27,"column_start":5,"column_end":8}},{"value":"/ # Note","span":{"file_name":"C:\\Users\\CYM\\scoop\\persist\\rustup\\.cargo\\registry\\src\\github.com-1ecc6299db9ec823\\hyper-tls-0.4.3\\src\\client.rs","byte_start":1593,"byte_end":1603,"line_start":28,"line_end":28,"column_start":5,"column_end":15}},{"value":"/","span":{"file_name":"C:\\Users\\CYM\\scoop\\persist\\rustup\\.cargo\\registry\\src\\github.com-1ecc6299db9ec823\\hyper-tls-0.4.3\\src\\client.rs","byte_start":1608,"byte_end":1611,"line_start":29,"line_end":29,"column_start":5,"column_end":8}},{"value":"/ By default this connector will use plain HTTP if the URL provded uses","span":{"file_name":"C:\\Users\\CYM\\scoop\\persist\\rustup\\.cargo\\registry\\src\\github.com-1ecc6299db9ec823\\hyper-tls-0.4.3\\src\\client.rs","byte_start":1616,"byte_end":1689,"line_start":30,"line_end":30,"column_start":5,"column_end":78}},{"value":"/ the HTTP scheme (eg: http://example.com/).","span":{"file_name":"C:\\Users\\CYM\\scoop\\persist\\rustup\\.cargo\\registry\\src\\github.com-1ecc6299db9ec823\\hyper-tls-0.4.3\\src\\client.rs","byte_start":1694,"byte_end":1740,"line_start":31,"line_end":31,"column_start":5,"column_end":51}},{"value":"/","span":{"file_name":"C:\\Users\\CYM\\scoop\\persist\\rustup\\.cargo\\registry\\src\\github.com-1ecc6299db9ec823\\hyper-tls-0.4.3\\src\\client.rs","byte_start":1745,"byte_end":1748,"line_start":32,"line_end":32,"column_start":5,"column_end":8}},{"value":"/ If you would like to force the use of HTTPS then call https_only(true)","span":{"file_name":"C:\\Users\\CYM\\scoop\\persist\\rustup\\.cargo\\registry\\src\\github.com-1ecc6299db9ec823\\hyper-tls-0.4.3\\src\\client.rs","byte_start":1753,"byte_end":1827,"line_start":33,"line_end":33,"column_start":5,"column_end":79}},{"value":"/ on the returned connector.","span":{"file_name":"C:\\Users\\CYM\\scoop\\persist\\rustup\\.cargo\\registry\\src\\github.com-1ecc6299db9ec823\\hyper-tls-0.4.3\\src\\client.rs","byte_start":1832,"byte_end":1862,"line_start":34,"line_end":34,"column_start":5,"column_end":35}},{"value":"/","span":{"file_name":"C:\\Users\\CYM\\scoop\\persist\\rustup\\.cargo\\registry\\src\\github.com-1ecc6299db9ec823\\hyper-tls-0.4.3\\src\\client.rs","byte_start":1867,"byte_end":1870,"line_start":35,"line_end":35,"column_start":5,"column_end":8}},{"value":"/ # Panics","span":{"file_name":"C:\\Users\\CYM\\scoop\\persist\\rustup\\.cargo\\registry\\src\\github.com-1ecc6299db9ec823\\hyper-tls-0.4.3\\src\\client.rs","byte_start":1875,"byte_end":1887,"line_start":36,"line_end":36,"column_start":5,"column_end":17}},{"value":"/","span":{"file_name":"C:\\Users\\CYM\\scoop\\persist\\rustup\\.cargo\\registry\\src\\github.com-1ecc6299db9ec823\\hyper-tls-0.4.3\\src\\client.rs","byte_start":1892,"byte_end":1895,"line_start":37,"line_end":37,"column_start":5,"column_end":8}},{"value":"/ This will panic if the underlying TLS context could not be created.","span":{"file_name":"C:\\Users\\CYM\\scoop\\persist\\rustup\\.cargo\\registry\\src\\github.com-1ecc6299db9ec823\\hyper-tls-0.4.3\\src\\client.rs","byte_start":1900,"byte_end":1971,"line_start":38,"line_end":38,"column_start":5,"column_end":76}},{"value":"/","span":{"file_name":"C:\\Users\\CYM\\scoop\\persist\\rustup\\.cargo\\registry\\src\\github.com-1ecc6299db9ec823\\hyper-tls-0.4.3\\src\\client.rs","byte_start":1976,"byte_end":1979,"line_start":39,"line_end":39,"column_start":5,"column_end":8}},{"value":"/ To handle that error yourself, you can use the `HttpsConnector::from`","span":{"file_name":"C:\\Users\\CYM\\scoop\\persist\\rustup\\.cargo\\registry\\src\\github.com-1ecc6299db9ec823\\hyper-tls-0.4.3\\src\\client.rs","byte_start":1984,"byte_end":2057,"line_start":40,"line_end":40,"column_start":5,"column_end":78}},{"value":"/ constructor after trying to make a `TlsConnector`.","span":{"file_name":"C:\\Users\\CYM\\scoop\\persist\\rustup\\.cargo\\registry\\src\\github.com-1ecc6299db9ec823\\hyper-tls-0.4.3\\src\\client.rs","byte_start":2062,"byte_end":2116,"line_start":41,"line_end":41,"column_start":5,"column_end":59}}]},{"kind":"Method","id":{"krate":0,"index":37},"span":{"file_name":"C:\\Users\\CYM\\scoop\\persist\\rustup\\.cargo\\registry\\src\\github.com-1ecc6299db9ec823\\hyper-tls-0.4.3\\src\\client.rs","byte_start":2803,"byte_end":2813,"line_start":65,"line_end":65,"column_start":12,"column_end":22},"name":"https_only","qualname":"<HttpsConnector<T>>::https_only","value":"pub fn https_only(&mut Self, bool)","parent":null,"children":[],"decl_id":null,"docs":" Force the use of HTTPS when connecting.","sig":null,"attributes":[{"value":"/ Force the use of HTTPS when connecting.","span":{"file_name":"C:\\Users\\CYM\\scoop\\persist\\rustup\\.cargo\\registry\\src\\github.com-1ecc6299db9ec823\\hyper-tls-0.4.3\\src\\client.rs","byte_start":2669,"byte_end":2712,"line_start":62,"line_end":62,"column_start":5,"column_end":48}},{"value":"/","span":{"file_name":"C:\\Users\\CYM\\scoop\\persist\\rustup\\.cargo\\registry\\src\\github.com-1ecc6299db9ec823\\hyper-tls-0.4.3\\src\\client.rs","byte_start":2717,"byte_end":2720,"line_start":63,"line_end":63,"column_start":5,"column_end":8}},{"value":"/ If a URL is not `https` when connecting, an error is returned.","span":{"file_name":"C:\\Users\\CYM\\scoop\\persist\\rustup\\.cargo\\registry\\src\\github.com-1ecc6299db9ec823\\hyper-tls-0.4.3\\src\\client.rs","byte_start":2725,"byte_end":2791,"line_start":64,"line_end":64,"column_start":5,"column_end":71}}]},{"kind":"Method","id":{"krate":0,"index":38},"span":{"file_name":"C:\\Users\\CYM\\scoop\\persist\\rustup\\.cargo\\registry\\src\\github.com-1ecc6299db9ec823\\hyper-tls-0.4.3\\src\\client.rs","byte_start":2942,"byte_end":2960,"line_start":71,"line_end":71,"column_start":12,"column_end":30},"name":"new_with_connector","qualname":"<HttpsConnector<T>>::new_with_connector","value":"pub fn new_with_connector(T) -> Self","parent":null,"children":[],"decl_id":null,"docs":" With connector constructor\n \n","sig":null,"attributes":[{"value":"/ With connector constructor","span":{"file_name":"C:\\Users\\CYM\\scoop\\persist\\rustup\\.cargo\\registry\\src\\github.com-1ecc6299db9ec823\\hyper-tls-0.4.3\\src\\client.rs","byte_start":2891,"byte_end":2921,"line_start":69,"line_end":69,"column_start":5,"column_end":35}},{"value":"/ ","span":{"file_name":"C:\\Users\\CYM\\scoop\\persist\\rustup\\.cargo\\registry\\src\\github.com-1ecc6299db9ec823\\hyper-tls-0.4.3\\src\\client.rs","byte_start":2926,"byte_end":2930,"line_start":70,"line_end":70,"column_start":5,"column_end":9}}]},{"kind":"Struct","id":{"krate":0,"index":61},"span":{"file_name":"C:\\Users\\CYM\\scoop\\persist\\rustup\\.cargo\\registry\\src\\github.com-1ecc6299db9ec823\\hyper-tls-0.4.3\\src\\client.rs","byte_start":5520,"byte_end":5535,"line_start":150,"line_end":150,"column_start":12,"column_end":27},"name":"HttpsConnecting","qualname":"::client::HttpsConnecting","value":"","parent":null,"children":[],"decl_id":null,"docs":" A Future representing work to connect to a URL, and a TLS handshake.\n","sig":null,"attributes":[{"value":"/ A Future representing work to connect to a URL, and a TLS handshake.","span":{"file_name":"C:\\Users\\CYM\\scoop\\persist\\rustup\\.cargo\\registry\\src\\github.com-1ecc6299db9ec823\\hyper-tls-0.4.3\\src\\client.rs","byte_start":5436,"byte_end":5508,"line_start":149,"line_end":149,"column_start":1,"column_end":73}}]},{"kind":"TupleVariant","id":{"krate":0,"index":94},"span":{"file_name":"C:\\Users\\CYM\\scoop\\persist\\rustup\\.cargo\\registry\\src\\github.com-1ecc6299db9ec823\\hyper-tls-0.4.3\\src\\stream.rs","byte_start":6624,"byte_end":6628,"line_start":14,"line_end":14,"column_start":5,"column_end":9},"name":"Http","qualname":"::stream::MaybeHttpsStream::Http","value":"MaybeHttpsStream::Http(T)","parent":{"krate":0,"index":92},"children":[],"decl_id":null,"docs":" A stream over plain text.\n","sig":null,"attributes":[{"value":"/ A stream over plain text.","span":{"file_name":"C:\\Users\\CYM\\scoop\\persist\\rustup\\.cargo\\registry\\src\\github.com-1ecc6299db9ec823\\hyper-tls-0.4.3\\src\\stream.rs","byte_start":6590,"byte_end":6619,"line_start":13,"line_end":13,"column_start":5,"column_end":34}}]},{"kind":"TupleVariant","id":{"krate":0,"index":97},"span":{"file_name":"C:\\Users\\CYM\\scoop\\persist\\rustup\\.cargo\\registry\\src\\github.com-1ecc6299db9ec823\\hyper-tls-0.4.3\\src\\stream.rs","byte_start":6674,"byte_end":6679,"line_start":16,"line_end":16,"column_start":5,"column_end":10},"name":"Https","qualname":"::stream::MaybeHttpsStream::Https","value":"MaybeHttpsStream::Https(TlsStream<T>)","parent":{"krate":0,"index":92},"children":[],"decl_id":null,"docs":" A stream protected with TLS.\n","sig":null,"attributes":[{"value":"/ A stream protected with TLS.","span":{"file_name":"C:\\Users\\CYM\\scoop\\persist\\rustup\\.cargo\\registry\\src\\github.com-1ecc6299db9ec823\\hyper-tls-0.4.3\\src\\stream.rs","byte_start":6637,"byte_end":6669,"line_start":15,"line_end":15,"column_start":5,"column_end":37}}]},{"kind":"Enum","id":{"krate":0,"index":92},"span":{"file_name":"C:\\Users\\CYM\\scoop\\persist\\rustup\\.cargo\\registry\\src\\github.com-1ecc6299db9ec823\\hyper-tls-0.4.3\\src\\stream.rs","byte_start":6564,"byte_end":6580,"line_start":12,"line_end":12,"column_start":10,"column_end":26},"name":"MaybeHttpsStream","qualname":"::stream::MaybeHttpsStream","value":"pub enum MaybeHttpsStream<T> {\n\n    /// A stream over plain text.\n    Http(T),\n\n    /// A stream protected with TLS.\n    Https(TlsStream<T>),\n}","parent":null,"children":[{"krate":0,"index":94},{"krate":0,"index":97}],"decl_id":null,"docs":" A stream that might be protected with TLS.\n","sig":null,"attributes":[{"value":"/ A stream that might be protected with TLS.","span":{"file_name":"C:\\Users\\CYM\\scoop\\persist\\rustup\\.cargo\\registry\\src\\github.com-1ecc6299db9ec823\\hyper-tls-0.4.3\\src\\stream.rs","byte_start":6508,"byte_end":6554,"line_start":11,"line_end":11,"column_start":1,"column_end":47}}]}],"impls":[{"id":0,"kind":"Inherent","span":{"file_name":"C:\\Users\\CYM\\scoop\\persist\\rustup\\.cargo\\registry\\src\\github.com-1ecc6299db9ec823\\hyper-tls-0.4.3\\src\\client.rs","byte_start":1345,"byte_end":1359,"line_start":22,"line_end":22,"column_start":6,"column_end":20},"value":"","parent":null,"children":[{"krate":0,"index":28},{"krate":0,"index":31}],"docs":"","sig":null,"attributes":[]},{"id":1,"kind":"Direct","span":{"file_name":"C:\\Users\\CYM\\scoop\\persist\\rustup\\.cargo\\registry\\src\\github.com-1ecc6299db9ec823\\hyper-tls-0.4.3\\src\\client.rs","byte_start":2528,"byte_end":2542,"line_start":55,"line_end":55,"column_start":30,"column_end":44},"value":"","parent":null,"children":[{"krate":0,"index":34}],"docs":"","sig":null,"attributes":[]},{"id":2,"kind":"Inherent","span":{"file_name":"C:\\Users\\CYM\\scoop\\persist\\rustup\\.cargo\\registry\\src\\github.com-1ecc6299db9ec823\\hyper-tls-0.4.3\\src\\client.rs","byte_start":2645,"byte_end":2659,"line_start":61,"line_end":61,"column_start":9,"column_end":23},"value":"","parent":null,"children":[{"krate":0,"index":37},{"krate":0,"index":38}],"docs":"","sig":null,"attributes":[]},{"id":3,"kind":"Direct","span":{"file_name":"C:\\Users\\CYM\\scoop\\persist\\rustup\\.cargo\\registry\\src\\github.com-1ecc6299db9ec823\\hyper-tls-0.4.3\\src\\client.rs","byte_start":3236,"byte_end":3250,"line_start":78,"line_end":78,"column_start":37,"column_end":51},"value":"","parent":null,"children":[{"krate":0,"index":43}],"docs":"","sig":null,"attributes":[]},{"id":4,"kind":"Direct","span":{"file_name":"C:\\Users\\CYM\\scoop\\persist\\rustup\\.cargo\\registry\\src\\github.com-1ecc6299db9ec823\\hyper-tls-0.4.3\\src\\client.rs","byte_start":3478,"byte_end":3492,"line_start":88,"line_end":88,"column_start":36,"column_end":50},"value":"","parent":null,"children":[{"krate":0,"index":46}],"docs":"","sig":null,"attributes":[]},{"id":5,"kind":"Direct","span":{"file_name":"C:\\Users\\CYM\\scoop\\persist\\rustup\\.cargo\\registry\\src\\github.com-1ecc6299db9ec823\\hyper-tls-0.4.3\\src\\client.rs","byte_start":3746,"byte_end":3760,"line_start":97,"line_end":97,"column_start":26,"column_end":40},"value":"","parent":null,"children":[{"krate":0,"index":49},{"krate":0,"index":50},{"krate":0,"index":51},{"krate":0,"index":52},{"krate":0,"index":53}],"docs":"","sig":null,"attributes":[]},{"id":6,"kind":"Direct","span":{"file_name":"C:\\Users\\CYM\\scoop\\persist\\rustup\\.cargo\\registry\\src\\github.com-1ecc6299db9ec823\\hyper-tls-0.4.3\\src\\client.rs","byte_start":5605,"byte_end":5620,"line_start":152,"line_end":152,"column_start":52,"column_end":67},"value":"","parent":null,"children":[{"krate":0,"index":67},{"krate":0,"index":68}],"docs":"","sig":null,"attributes":[]},{"id":7,"kind":"Direct","span":{"file_name":"C:\\Users\\CYM\\scoop\\persist\\rustup\\.cargo\\registry\\src\\github.com-1ecc6299db9ec823\\hyper-tls-0.4.3\\src\\client.rs","byte_start":5839,"byte_end":5854,"line_start":160,"line_end":160,"column_start":24,"column_end":39},"value":"","parent":null,"children":[{"krate":0,"index":71}],"docs":"","sig":null,"attributes":[]},{"id":8,"kind":"Direct","span":{"file_name":"C:\\Users\\CYM\\scoop\\persist\\rustup\\.cargo\\registry\\src\\github.com-1ecc6299db9ec823\\hyper-tls-0.4.3\\src\\client.rs","byte_start":6064,"byte_end":6088,"line_start":171,"line_end":171,"column_start":23,"column_end":47},"value":"","parent":null,"children":[{"krate":0,"index":73}],"docs":"","sig":null,"attributes":[]},{"id":9,"kind":"Direct","span":{"file_name":"C:\\Users\\CYM\\scoop\\persist\\rustup\\.cargo\\registry\\src\\github.com-1ecc6299db9ec823\\hyper-tls-0.4.3\\src\\client.rs","byte_start":6250,"byte_end":6274,"line_start":177,"line_end":177,"column_start":28,"column_end":52},"value":"","parent":null,"children":[],"docs":"","sig":null,"attributes":[]},{"id":10,"kind":"Direct","span":{"file_name":"C:\\Users\\CYM\\scoop\\persist\\rustup\\.cargo\\registry\\src\\github.com-1ecc6299db9ec823\\hyper-tls-0.4.3\\src\\stream.rs","byte_start":6771,"byte_end":6787,"line_start":21,"line_end":21,"column_start":36,"column_end":52},"value":"","parent":null,"children":[{"krate":0,"index":102}],"docs":"","sig":null,"attributes":[]},{"id":11,"kind":"Direct","span":{"file_name":"C:\\Users\\CYM\\scoop\\persist\\rustup\\.cargo\\registry\\src\\github.com-1ecc6299db9ec823\\hyper-tls-0.4.3\\src\\stream.rs","byte_start":7078,"byte_end":7094,"line_start":30,"line_end":30,"column_start":21,"column_end":37},"value":"","parent":null,"children":[{"krate":0,"index":105}],"docs":"","sig":null,"attributes":[]},{"id":12,"kind":"Direct","span":{"file_name":"C:\\Users\\CYM\\scoop\\persist\\rustup\\.cargo\\registry\\src\\github.com-1ecc6299db9ec823\\hyper-tls-0.4.3\\src\\stream.rs","byte_start":7210,"byte_end":7226,"line_start":36,"line_end":36,"column_start":32,"column_end":48},"value":"","parent":null,"children":[{"krate":0,"index":108}],"docs":"","sig":null,"attributes":[]},{"id":13,"kind":"Direct","span":{"file_name":"C:\\Users\\CYM\\scoop\\persist\\rustup\\.cargo\\registry\\src\\github.com-1ecc6299db9ec823\\hyper-tls-0.4.3\\src\\stream.rs","byte_start":7377,"byte_end":7393,"line_start":42,"line_end":42,"column_start":55,"column_end":71},"value":"","parent":null,"children":[{"krate":0,"index":111},{"krate":0,"index":112},{"krate":0,"index":113}],"docs":"","sig":null,"attributes":[]},{"id":14,"kind":"Direct","span":{"file_name":"C:\\Users\\CYM\\scoop\\persist\\rustup\\.cargo\\registry\\src\\github.com-1ecc6299db9ec823\\hyper-tls-0.4.3\\src\\stream.rs","byte_start":8494,"byte_end":8510,"line_start":76,"line_end":76,"column_start":56,"column_end":72},"value":"","parent":null,"children":[{"krate":0,"index":117},{"krate":0,"index":118},{"krate":0,"index":120},{"krate":0,"index":121}],"docs":"","sig":null,"attributes":[]},{"id":15,"kind":"Direct","span":{"file_name":"C:\\Users\\CYM\\scoop\\persist\\rustup\\.cargo\\registry\\src\\github.com-1ecc6299db9ec823\\hyper-tls-0.4.3\\src\\stream.rs","byte_start":9928,"byte_end":9944,"line_start":118,"line_end":118,"column_start":69,"column_end":85},"value":"","parent":null,"children":[{"krate":0,"index":124}],"docs":"","sig":null,"attributes":[]}],"refs":[],"macro_refs":[],"relations":[{"span":{"file_name":"C:\\Users\\CYM\\scoop\\persist\\rustup\\.cargo\\registry\\src\\github.com-1ecc6299db9ec823\\hyper-tls-0.4.3\\src\\client.rs","byte_start":1345,"byte_end":1359,"line_start":22,"line_end":22,"column_start":6,"column_end":20},"kind":{"Impl":{"id":0}},"from":{"krate":0,"index":125},"to":{"krate":4294967295,"index":4294967295}},{"span":{"file_name":"C:\\Users\\CYM\\scoop\\persist\\rustup\\.cargo\\registry\\src\\github.com-1ecc6299db9ec823\\hyper-tls-0.4.3\\src\\client.rs","byte_start":2528,"byte_end":2542,"line_start":55,"line_end":55,"column_start":30,"column_end":44},"kind":{"Impl":{"id":1}},"from":{"krate":0,"index":125},"to":{"krate":2,"index":2022}},{"span":{"file_name":"C:\\Users\\CYM\\scoop\\persist\\rustup\\.cargo\\registry\\src\\github.com-1ecc6299db9ec823\\hyper-tls-0.4.3\\src\\client.rs","byte_start":2645,"byte_end":2659,"line_start":61,"line_end":61,"column_start":9,"column_end":23},"kind":{"Impl":{"id":2}},"from":{"krate":0,"index":125},"to":{"krate":4294967295,"index":4294967295}},{"span":{"file_name":"C:\\Users\\CYM\\scoop\\persist\\rustup\\.cargo\\registry\\src\\github.com-1ecc6299db9ec823\\hyper-tls-0.4.3\\src\\client.rs","byte_start":3236,"byte_end":3250,"line_start":78,"line_end":78,"column_start":37,"column_end":51},"kind":{"Impl":{"id":3}},"from":{"krate":0,"index":125},"to":{"krate":2,"index":1952}},{"span":{"file_name":"C:\\Users\\CYM\\scoop\\persist\\rustup\\.cargo\\registry\\src\\github.com-1ecc6299db9ec823\\hyper-tls-0.4.3\\src\\client.rs","byte_start":3478,"byte_end":3492,"line_start":88,"line_end":88,"column_start":36,"column_end":50},"kind":{"Impl":{"id":4}},"from":{"krate":0,"index":125},"to":{"krate":2,"index":6562}},{"span":{"file_name":"C:\\Users\\CYM\\scoop\\persist\\rustup\\.cargo\\registry\\src\\github.com-1ecc6299db9ec823\\hyper-tls-0.4.3\\src\\client.rs","byte_start":3746,"byte_end":3760,"line_start":97,"line_end":97,"column_start":26,"column_end":40},"kind":{"Impl":{"id":5}},"from":{"krate":0,"index":125},"to":{"krate":47,"index":7}},{"span":{"file_name":"C:\\Users\\CYM\\scoop\\persist\\rustup\\.cargo\\registry\\src\\github.com-1ecc6299db9ec823\\hyper-tls-0.4.3\\src\\client.rs","byte_start":5605,"byte_end":5620,"line_start":152,"line_end":152,"column_start":52,"column_end":67},"kind":{"Impl":{"id":6}},"from":{"krate":0,"index":61},"to":{"krate":2,"index":9060}},{"span":{"file_name":"C:\\Users\\CYM\\scoop\\persist\\rustup\\.cargo\\registry\\src\\github.com-1ecc6299db9ec823\\hyper-tls-0.4.3\\src\\client.rs","byte_start":5839,"byte_end":5854,"line_start":160,"line_end":160,"column_start":24,"column_end":39},"kind":{"Impl":{"id":7}},"from":{"krate":0,"index":61},"to":{"krate":2,"index":6562}},{"span":{"file_name":"C:\\Users\\CYM\\scoop\\persist\\rustup\\.cargo\\registry\\src\\github.com-1ecc6299db9ec823\\hyper-tls-0.4.3\\src\\client.rs","byte_start":6064,"byte_end":6088,"line_start":171,"line_end":171,"column_start":23,"column_end":47},"kind":{"Impl":{"id":8}},"from":{"krate":0,"index":133},"to":{"krate":2,"index":6567}},{"span":{"file_name":"C:\\Users\\CYM\\scoop\\persist\\rustup\\.cargo\\registry\\src\\github.com-1ecc6299db9ec823\\hyper-tls-0.4.3\\src\\client.rs","byte_start":6250,"byte_end":6274,"line_start":177,"line_end":177,"column_start":28,"column_end":52},"kind":{"Impl":{"id":9}},"from":{"krate":0,"index":133},"to":{"krate":1,"index":1720}},{"span":{"file_name":"C:\\Users\\CYM\\scoop\\persist\\rustup\\.cargo\\registry\\src\\github.com-1ecc6299db9ec823\\hyper-tls-0.4.3\\src\\stream.rs","byte_start":6771,"byte_end":6787,"line_start":21,"line_end":21,"column_start":36,"column_end":52},"kind":{"Impl":{"id":10}},"from":{"krate":0,"index":92},"to":{"krate":2,"index":6562}},{"span":{"file_name":"C:\\Users\\CYM\\scoop\\persist\\rustup\\.cargo\\registry\\src\\github.com-1ecc6299db9ec823\\hyper-tls-0.4.3\\src\\stream.rs","byte_start":7078,"byte_end":7094,"line_start":30,"line_end":30,"column_start":21,"column_end":37},"kind":{"Impl":{"id":11}},"from":{"krate":0,"index":92},"to":{"krate":2,"index":1952}},{"span":{"file_name":"C:\\Users\\CYM\\scoop\\persist\\rustup\\.cargo\\registry\\src\\github.com-1ecc6299db9ec823\\hyper-tls-0.4.3\\src\\stream.rs","byte_start":7210,"byte_end":7226,"line_start":36,"line_end":36,"column_start":32,"column_end":48},"kind":{"Impl":{"id":12}},"from":{"krate":0,"index":92},"to":{"krate":2,"index":1952}},{"span":{"file_name":"C:\\Users\\CYM\\scoop\\persist\\rustup\\.cargo\\registry\\src\\github.com-1ecc6299db9ec823\\hyper-tls-0.4.3\\src\\stream.rs","byte_start":7377,"byte_end":7393,"line_start":42,"line_end":42,"column_start":55,"column_end":71},"kind":{"Impl":{"id":13}},"from":{"krate":0,"index":92},"to":{"krate":30,"index":215}},{"span":{"file_name":"C:\\Users\\CYM\\scoop\\persist\\rustup\\.cargo\\registry\\src\\github.com-1ecc6299db9ec823\\hyper-tls-0.4.3\\src\\stream.rs","byte_start":8494,"byte_end":8510,"line_start":76,"line_end":76,"column_start":56,"column_end":72},"kind":{"Impl":{"id":14}},"from":{"krate":0,"index":92},"to":{"krate":30,"index":271}},{"span":{"file_name":"C:\\Users\\CYM\\scoop\\persist\\rustup\\.cargo\\registry\\src\\github.com-1ecc6299db9ec823\\hyper-tls-0.4.3\\src\\stream.rs","byte_start":9928,"byte_end":9944,"line_start":118,"line_end":118,"column_start":69,"column_end":85},"kind":{"Impl":{"id":15}},"from":{"krate":0,"index":92},"to":{"krate":17,"index":866}}]}